tft_report/__init__.py
tft_report-1.0.0.dist-info/licenses/LICENSE
tft_report-1.0.0.dist-info/METADATA
tft_report-1.0.0.dist-info/WHEEL
tft_report-1.0.0.dist-info/top_level.txt
tft_report-1.0.0.dist-info/RECORD
