Metadata-Version: 2.4
Name: tft-report
Version: 1.0.0
Summary: Automated TFT modeling with publication-ready report generation
Home-page: https://github.com/sdkparkforbi/tft-report
Author: Your Name
Author-email: Your Name <your.email@example.com>
License: MIT
Project-URL: Homepage, https://github.com/sdkparkforbi/tft-report
Project-URL: Repository, https://github.com/sdkparkforbi/tft-report
Classifier: Development Status :: 4 - Beta
Classifier: Intended Audience :: Science/Research
Classifier: License :: OSI Approved :: MIT License
Classifier: Operating System :: OS Independent
Classifier: Programming Language :: Python :: 3
Classifier: Programming Language :: Python :: 3.9
Classifier: Programming Language :: Python :: 3.10
Classifier: Programming Language :: Python :: 3.11
Classifier: Programming Language :: Python :: 3.12
Classifier: Topic :: Scientific/Engineering :: Artificial Intelligence
Requires-Python: >=3.9
License-File: LICENSE
Requires-Dist: pandas>=1.5.0
Requires-Dist: numpy>=1.21.0
Requires-Dist: matplotlib>=3.5.0
Requires-Dist: python-docx>=0.8.0
Requires-Dist: openai>=1.0.0
Requires-Dist: torch>=2.0.0
Requires-Dist: pytorch-forecasting>=1.0.0
Requires-Dist: lightning>=2.0.0
Dynamic: author
Dynamic: home-page
Dynamic: license-file
Dynamic: requires-python
